Metadata-Version: 2.1
Name: package-super-example
Version: 0.0.8
Summary: description text
Home-page: UNKNOWN
License: UNKNOWN
Platform: UNKNOWN
